LICENSE.md
MANIFEST.in
README.md
requirements.txt
setup.cfg
setup.py
haproxy_health_check/__init__.py
haproxy_health_check/haproxy_health_check.py
haproxy_health_check.egg-info/PKG-INFO
haproxy_health_check.egg-info/SOURCES.txt
haproxy_health_check.egg-info/dependency_links.txt
haproxy_health_check.egg-info/entry_points.txt
haproxy_health_check.egg-info/requires.txt
haproxy_health_check.egg-info/top_level.txt