Metadata-Version: 1.1
Name: haproxy-health-check
Version: 0.0.1
Summary: HAProxy Health Check for EXABGP
Home-page: https://github.com/kaplun/haproxy-health-check
Author: Samuele Kaplun
Author-email: kaplun@protonmail.com
License: BSD
Download-URL: https://github.com/kaplun/haproxy-health-check/tarball/0.0.1
Platform: UNKNOWN
Classifier: Development Status :: 3 - Alpha
Classifier: Intended Audience :: Developers
Classifier: Programming Language :: Python :: 3
